{
  "publicPath": "/assets/",
  "all": [
    "../server/index.spa.html",
    "../server/index.ssr.html",
    "0c3a7a100cc5e1348a53.js",
    "3bc696b6d104b814fdf5.js",
    "6caa9f31c7c3afc0d05e.js",
    "738fbe8f0e0f8b8c4ae6.js",
    "854c1ebf747c03a3243f.js",
    "872b8aabeeab1c4c019b.js",
    "894b38600c848d977216.js",
    "LICENSES",
    "e8787bffd18174a467a0.js",
    "e9cd64059dbcf35cb990.js",
    "f41240acdbb542ee606c.js"
  ],
  "initial": [
    "0c3a7a100cc5e1348a53.js",
    "738fbe8f0e0f8b8c4ae6.js",
    "6caa9f31c7c3afc0d05e.js",
    "e9cd64059dbcf35cb990.js"
  ],
  "async": [
    "3bc696b6d104b814fdf5.js",
    "854c1ebf747c03a3243f.js",
    "872b8aabeeab1c4c019b.js",
    "894b38600c848d977216.js",
    "e8787bffd18174a467a0.js",
    "f41240acdbb542ee606c.js"
  ],
  "modules": {
    "42620896": [
      5
    ],
    "45500236": [
      5
    ],
    "56462786": [
      7
    ],
    "76968004": [
      5
    ],
    "4a5fd36a": [
      11
    ],
    "845a6bfa": [
      5
    ],
    "d1dc02d0": [
      5
    ],
    "1ef42ae4": [
      5
    ],
    "14057ef8": [
      5
    ],
    "6f717af0": [
      5
    ],
    "ff61cdb8": [
      5
    ],
    "6b562652": [
      5
    ],
    "e9ba3bc8": [
      5
    ],
    "9d6e0402": [
      5
    ],
    "ecf007de": [
      5
    ],
    "757dc249": [
      5
    ],
    "26e7766a": [
      5
    ],
    "8f6c5c04": [
      4
    ],
    "40e0a2b9": [
      4
    ],
    "0c0e060c": [
      4
    ],
    "b3587c3e": [
      5
    ],
    "2dff132e": [
      5
    ],
    "6ae85b9d": [
      5
    ],
    "2583bba9": [
      11
    ],
    "759c926c": [
      11
    ],
    "d9713920": [
      11
    ],
    "6e46b310": [
      11
    ],
    "8037ee42": [
      11
    ],
    "6d8a7dcc": [
      11
    ],
    "f5ae858c": [
      11
    ],
    "008b8585": [
      11
    ],
    "3ba0c5e9": [
      11
    ],
    "94f4ef14": [
      11
    ],
    "6db8fc92": [
      11
    ],
    "39196c11": [
      11
    ],
    "6aeeed26": [
      11
    ],
    "6dbd2c44": [
      11
    ],
    "69895d5c": [
      11
    ],
    "5b59dc25": [
      11
    ],
    "2c83dbfe": [
      11
    ],
    "25bf039c": [
      11
    ],
    "5424a666": [
      11
    ],
    "12fb9ea4": [
      11
    ],
    "168c4f66": [
      11
    ],
    "8c32ca3e": [
      11
    ],
    "0c8ef3ff": [
      11
    ],
    "5a44eb1e": [
      11
    ],
    "9d3081b4": [
      11
    ],
    "5340c15a": [
      11
    ],
    "f4c479ce": [
      11
    ],
    "1fa98ff7": [
      11
    ],
    "c7f72128": [
      11
    ],
    "2f325c96": [
      11
    ],
    "6a1443ad": [
      11
    ],
    "5b74f896": [
      11
    ],
    "f0395a3a": [
      11
    ],
    "139984e4": [
      11
    ],
    "284c5f06": [
      11
    ],
    "6bb56f5c": [
      11
    ],
    "1fffd7c1": [
      11
    ],
    "ca945d06": [
      11
    ],
    "448ea71c": [
      11
    ],
    "c884cb42": [
      11
    ],
    "20f45cb6": [
      11
    ],
    "a18fb070": [
      11
    ],
    "7b3ba235": [
      11
    ],
    "9fd93140": [
      11
    ],
    "070eaa19": [
      11
    ],
    "a0270cca": [
      11
    ],
    "24ddb94f": [
      11
    ],
    "4aaabe93": [
      11
    ],
    "879dcbcc": [
      11
    ],
    "4dc8d9f7": [
      11
    ],
    "22523ed5": [
      11
    ],
    "55a31dd0": [
      11
    ],
    "46e10e30": [
      11
    ],
    "53938c0c": [
      11
    ],
    "667ee311": [
      11
    ],
    "0b36260d": [
      11
    ],
    "ae442f6e": [
      11
    ],
    "5af6973b": [
      11
    ],
    "b71c0be8": [
      5
    ],
    "44a79ac6": [
      5
    ],
    "bc2274ee": [
      5
    ],
    "758dcfcc": [
      5
    ],
    "699d6c2f": [
      5
    ],
    "04ce8e89": [
      5
    ],
    "0bb3f62a": [
      5
    ],
    "79b18e40": [
      5
    ],
    "6127141b": [
      5
    ],
    "7faab356": [
      5
    ],
    "2e1dd47a": [
      5
    ],
    "59372e0c": [
      5
    ],
    "05575048": [
      5
    ],
    "70c0a861": [
      5
    ],
    "05f498ae": [
      5
    ],
    "372ac2ba": [
      5
    ],
    "b139dc1c": [
      5
    ],
    "596df55f": [
      5
    ],
    "1ab71384": [
      5
    ],
    "cfcb79fa": [
      5
    ],
    "993f20f6": [
      4
    ],
    "51ad26c8": [
      5
    ],
    "1b677913": [
      5
    ],
    "08ecd03a": [
      5
    ],
    "d934f8c2": [
      5
    ],
    "2317067e": [
      5
    ],
    "5f60e36e": [
      5
    ],
    "6fa7d500": [
      5
    ],
    "59d5a6c5": [
      5
    ],
    "21ca2e7d": [
      5
    ],
    "4049b4b2": [
      5
    ],
    "66779b46": [
      5
    ],
    "049d2c19": [
      5
    ],
    "52e2ca86": [
      5
    ],
    "948a6e72": [
      5
    ],
    "a48d43ec": [
      5
    ],
    "4e6a284d": [
      5
    ],
    "a491cfa2": [
      5
    ],
    "636ed9b4": [
      5
    ],
    "65f6647c": [
      5
    ],
    "fed3d09e": [
      5
    ],
    "7c00d3ae": [
      5
    ],
    "a6517266": [
      5
    ],
    "89bb90ca": [
      11
    ],
    "271ea7b2": [
      11
    ],
    "0b1a7ec9": [
      11
    ],
    "73ff9d7a": [
      11
    ],
    "b7d8da98": [
      11
    ],
    "6f4b1d3b": [
      11
    ],
    "12886b44": [
      11
    ],
    "7a83b275": [
      11
    ],
    "5cd3dbed": [
      11
    ],
    "0f250e19": [
      11
    ],
    "06c83ca6": [
      11
    ],
    "70dfbf80": [
      11
    ],
    "6b088dc4": [
      5
    ],
    "4b56cc54": [
      5
    ],
    "040f26b4": [
      5
    ],
    "6cde00ca": [
      5
    ],
    "a49ae70e": [
      5
    ],
    "3bb672ea": [
      5
    ],
    "65a8486e": [
      5
    ],
    "5dcf955f": [
      5
    ],
    "05900052": [
      5
    ],
    "56567c4c": [
      5
    ],
    "1369aa76": [
      5
    ],
    "d30651a2": [
      5
    ],
    "b83e343e": [
      11
    ],
    "517b84d2": [
      4
    ],
    "77da9995": [
      5
    ],
    "0d653f42": [
      5
    ],
    "b72ce5e0": [
      5
    ],
    "6c307598": [
      5
    ],
    "41e7d8a3": [
      5
    ],
    "4d374f7b": [
      5
    ],
    "ddaaf228": [
      5
    ],
    "aab18e4e": [
      5
    ],
    "9593d300": [
      5
    ],
    "6dd46590": [
      5
    ],
    "66db2f74": [
      5
    ],
    "19568c1d": [
      5
    ],
    "2ad465aa": [
      5
    ],
    "1c48c56b": [
      5
    ],
    "72ecb6d8": [
      5
    ],
    "3f191b53": [
      5
    ],
    "fa425c7c": [
      5
    ],
    "dc1be530": [
      5
    ],
    "8c460f90": [
      5
    ],
    "a32c7ee2": [
      5
    ],
    "48e9b5ca": [
      5
    ],
    "0fe8e266": [
      5
    ],
    "7a642754": [
      5
    ],
    "c7ab702e": [
      5
    ],
    "ec0dd21c": [
      5
    ],
    "acbc0fee": [
      5
    ],
    "70e022bc": [
      5
    ],
    "b3a7684c": [
      5
    ],
    "a57f5d14": [
      5
    ],
    "4b4ace14": [
      5
    ],
    "44d51fa2": [
      5
    ],
    "175d852c": [
      5
    ],
    "74348c45": [
      5
    ],
    "2cb90a57": [
      5
    ],
    "8cb21f84": [
      5
    ],
    "c01f093e": [
      4
    ],
    "3ff929a7": [
      5
    ],
    "890b4d84": [
      4
    ],
    "5b050a42": [
      5
    ],
    "c6982104": [
      5
    ],
    "58cbdf3b": [
      4
    ],
    "bc1f4fc2": [
      4
    ],
    "24a410df": [
      11
    ],
    "649e9bd6": [
      11
    ],
    "49a7f308": [
      11
    ],
    "e8d32746": [
      5
    ],
    "b70b9c34": [
      5
    ],
    "409bb9ba": [
      5
    ],
    "9c249dd6": [
      5
    ],
    "cbbbff56": [
      5
    ],
    "3a590292": [
      5
    ],
    "120edcdb": [
      5
    ],
    "7cb7d17c": [
      5
    ],
    "a1e8ff1c": [
      5
    ],
    "3f75baf3": [
      5
    ],
    "2e2a357e": [
      5
    ],
    "bc82324c": [
      5
    ],
    "47794b3c": [
      5
    ],
    "531cf637": [
      5
    ],
    "7174f675": [
      5
    ],
    "7a7a1d0e": [
      5
    ],
    "9eaa7c60": [
      5
    ],
    "4996d593": [
      5
    ],
    "ec23c90c": [
      5
    ],
    "2630cb3c": [
      5
    ],
    "55d19cb0": [
      5
    ],
    "7d7499c9": [
      5
    ],
    "6c732372": [
      5
    ],
    "48eb1ff4": [
      5
    ],
    "08af9dc2": [
      5
    ],
    "25c83b60": [
      5
    ],
    "2c3c774e": [
      5
    ],
    "568a8598": [
      5
    ],
    "74bc5ba8": [
      5
    ],
    "3d0c4e29": [
      5
    ],
    "e3277474": [
      5
    ],
    "86077ef4": [
      5
    ],
    "46ddcd3a": [
      5
    ],
    "015f6581": [
      5
    ],
    "3f48272f": [
      5
    ],
    "920419ca": [
      5
    ],
    "7b743007": [
      11
    ],
    "95af65b8": [
      11
    ],
    "3fb38cda": [
      11
    ],
    "7d478370": [
      11
    ],
    "414e9437": [
      5
    ],
    "7e473cca": [
      5
    ],
    "e256acd6": [
      5
    ],
    "a1a1b748": [
      5
    ],
    "67233ebb": [
      5
    ],
    "6c1566f2": [
      5
    ],
    "2f0d275c": [
      5
    ],
    "217c1a7a": [
      5
    ],
    "0d67f08f": [
      5
    ],
    "6c8571ee": [
      5
    ],
    "161fd514": [
      5
    ],
    "3a378304": [
      5
    ],
    "7ea59826": [
      5
    ],
    "6947f5c8": [
      5
    ],
    "81fad8d2": [
      5
    ],
    "54151ae4": [
      5
    ],
    "b6c37c46": [
      11
    ],
    "b2972e40": [
      11
    ],
    "5f83f457": [
      11
    ],
    "619a1b5a": [
      11
    ],
    "7a245e20": [
      11
    ],
    "9c867706": [
      11
    ],
    "063fbca7": [
      11
    ],
    "46ee7604": [
      11
    ],
    "ad05eaa0": [
      11
    ],
    "2ba877e6": [
      11
    ],
    "0e852a89": [
      11
    ],
    "fa219368": [
      11
    ],
    "1c41074e": [
      11
    ],
    "b6108114": [
      11
    ],
    "641a2cdb": [
      4
    ],
    "68916ef6": [
      11
    ],
    "23c06922": [
      11
    ],
    "7374105a": [
      11
    ],
    "06dba550": [
      11
    ],
    "2f6e2d5c": [
      4
    ],
    "2f3b08a0": [
      6
    ],
    "6b951e3c": [
      7
    ],
    "c3ee446e": [
      7
    ],
    "3e73b3b4": [
      10
    ],
    "e3ab8c12": [
      12
    ],
    "8d6bbb5c": [
      12
    ],
    "7f10f11c": [
      12
    ],
    "6d70d7ab": [
      3
    ],
    "a8474dea": [
      8
    ],
    "321855e8": [
      6
    ],
    "8e08f5ae": [
      6
    ],
    "0518e150": [
      7
    ],
    "072f0853": [
      7
    ],
    "638a1646": [
      7
    ],
    "a2046240": [
      7
    ],
    "e504f0dc": [
      10
    ],
    "074cb722": [
      10
    ],
    "35f4340b": [
      12
    ],
    "ab189964": [
      12
    ],
    "2a0e95be": [
      12
    ],
    "2dd0a21b": [
      12
    ],
    "0093b2f0": [
      12
    ],
    "4dca1665": [
      12
    ],
    "c4ba2282": [
      3
    ],
    "7e65c8c2": [
      3
    ],
    "40e7f977": [
      8
    ],
    "17ff86d8": [
      8
    ],
    "75c967d7": [
      12
    ],
    "4eae8cf8": [
      12
    ],
    "6ef99eff": [
      12
    ],
    "26d1ca98": [
      12
    ],
    "245f77cc": [
      12
    ],
    "14f046ba": [
      12
    ],
    "4ef47e32": [
      12
    ],
    "534b6587": [
      12
    ],
    "7b0055ba": [
      12
    ],
    "e8beee10": [
      12
    ],
    "42a6d384": [
      12
    ],
    "6f79b4f3": [
      12
    ],
    "0d42147f": [
      12
    ],
    "39f49c0c": [
      12
    ],
    "6900afc2": [
      12
    ],
    "2ccf6649": [
      7
    ],
    "61b57577": [
      7
    ],
    "3404f2cb": [
      7
    ],
    "f0f9f03a": [
      7
    ],
    "6cdc48d0": [
      7
    ],
    "23af6fa8": [
      7
    ],
    "2b4dc34c": [
      7
    ],
    "197ee41c": [
      7
    ],
    "7fc54451": [
      7
    ],
    "0a89ce44": [
      8
    ],
    "af968710": [
      8
    ],
    "3255e5d0": [
      8
    ],
    "48b8568c": [
      8
    ],
    "e7f1701a": [
      8
    ],
    "09632e1e": [
      8
    ],
    "69cc3347": [
      8
    ],
    "1433ded8": [
      8
    ],
    "d1230d4a": [
      8
    ],
    "81d1e29a": [
      8
    ],
    "49f983ce": [
      6
    ],
    "38f04d88": [
      6
    ],
    "3da6b03d": [
      6
    ],
    "f7e91960": [
      6
    ],
    "3a4e29d0": [
      6
    ],
    "29a8f02c": [
      10
    ],
    "a8172d20": [
      10
    ],
    "b2e21d6c": [
      10
    ],
    "39f9ce84": [
      10
    ],
    "6fc43d36": [
      10
    ],
    "5fe9363e": [
      3
    ],
    "2f80d925": [
      3
    ],
    "5aa7e19a": [
      3
    ],
    "554e6b91": [
      3
    ],
    "0b836538": [
      3
    ]
  },
  "assetsMapping": {
    "0c3a7a100cc5e1348a53.js": "6fca0322",
    "3bc696b6d104b814fdf5.js": "ae0b3444",
    "6caa9f31c7c3afc0d05e.js": "7ea1d828",
    "738fbe8f0e0f8b8c4ae6.js": "0859c165",
    "854c1ebf747c03a3243f.js": "2aff1868",
    "872b8aabeeab1c4c019b.js": "acf14974",
    "894b38600c848d977216.js": "2a130dde",
    "e8787bffd18174a467a0.js": "67c13ec2",
    "e9cd64059dbcf35cb990.js": "1a3ae26b",
    "f41240acdbb542ee606c.js": "3ad7aa6c"
  }
}