{
  "publicPath": "/assets/",
  "all": [
    "../server/index.spa.html",
    "../server/index.ssr.html",
    "10.ba10f2f.js",
    "LICENSES",
    "app.bafce3c.js",
    "pages/about.b419aed.js",
    "pages/blog/_name.2e89b62.js",
    "pages/blog/index.4949bf2.js",
    "pages/contact.f037173.js",
    "pages/index.998eb47.js",
    "pages/portfolio/_name.e743218.js",
    "pages/portfolio/index.e66de57.js",
    "runtime.7dce548.js",
    "vendors/commons.797aadd.js"
  ],
  "initial": [
    "runtime.7dce548.js",
    "vendors/commons.797aadd.js",
    "app.bafce3c.js"
  ],
  "async": [
    "10.ba10f2f.js",
    "pages/about.b419aed.js",
    "pages/blog/_name.2e89b62.js",
    "pages/blog/index.4949bf2.js",
    "pages/contact.f037173.js",
    "pages/index.998eb47.js",
    "pages/portfolio/_name.e743218.js",
    "pages/portfolio/index.e66de57.js"
  ],
  "modules": {
    "14101388": [
      4
    ],
    "21994464": [
      13
    ],
    "22202422": [
      9
    ],
    "29143950": [
      13
    ],
    "51218304": [
      6
    ],
    "65958628": [
      13
    ],
    "90045734": [
      13
    ],
    "98703276": [
      2
    ],
    "f4a64890": [
      13
    ],
    "542a666a": [
      4
    ],
    "49f486e2": [
      4
    ],
    "be597c98": [
      13
    ],
    "2c5c3342": [
      13
    ],
    "ecf8dda6": [
      13
    ],
    "ed59e742": [
      13
    ],
    "e8dd8908": [
      13
    ],
    "edc5e30c": [
      13
    ],
    "a0db8e7e": [
      13
    ],
    "7e81b584": [
      13
    ],
    "8f48482e": [
      13
    ],
    "6e8cdbe5": [
      13
    ],
    "64144b89": [
      13
    ],
    "6368d5fc": [
      13
    ],
    "6e112254": [
      4
    ],
    "7d6fd028": [
      4
    ],
    "075f3206": [
      4
    ],
    "a15095c8": [
      13
    ],
    "2f4e4ea9": [
      4
    ],
    "168cf86c": [
      4
    ],
    "07886763": [
      4
    ],
    "3e6d2c06": [
      4
    ],
    "2a67bf12": [
      4
    ],
    "4ae3d7cc": [
      4
    ],
    "e2195f8c": [
      4
    ],
    "1c28dc74": [
      4
    ],
    "52f33598": [
      4
    ],
    "0a561885": [
      4
    ],
    "308338ae": [
      4
    ],
    "61a32636": [
      4
    ],
    "63ea5df0": [
      4
    ],
    "ed2fd692": [
      4
    ],
    "3b2292ae": [
      4
    ],
    "d3fa0e28": [
      4
    ],
    "4a6ddbf1": [
      4
    ],
    "7e8c3b92": [
      4
    ],
    "4ad31648": [
      4
    ],
    "f0bcc1ec": [
      4
    ],
    "6a120763": [
      4
    ],
    "b93e9f10": [
      4
    ],
    "9897d130": [
      4
    ],
    "c095e212": [
      4
    ],
    "3740829f": [
      4
    ],
    "dcbf9cd2": [
      4
    ],
    "2ded3bf1": [
      4
    ],
    "a03405a2": [
      4
    ],
    "47fdcdc4": [
      4
    ],
    "14c4d7ee": [
      4
    ],
    "290dbeb8": [
      4
    ],
    "429bf4ac": [
      4
    ],
    "2391d2d8": [
      4
    ],
    "1af03e53": [
      4
    ],
    "9607e99e": [
      4
    ],
    "4c97631c": [
      4
    ],
    "342f6960": [
      4
    ],
    "19839e7a": [
      4
    ],
    "16a5c89d": [
      4
    ],
    "a566a59e": [
      4
    ],
    "9d37e4d6": [
      4
    ],
    "4654052b": [
      4
    ],
    "6c74ed96": [
      4
    ],
    "648c981e": [
      4
    ],
    "459f0256": [
      4
    ],
    "c1696f4e": [
      4
    ],
    "46a6cb38": [
      4
    ],
    "2d3cb1bb": [
      4
    ],
    "92c964e2": [
      4
    ],
    "619c0ad5": [
      4
    ],
    "6af7220e": [
      4
    ],
    "fd5d6832": [
      4
    ],
    "1499b4f4": [
      4
    ],
    "3b5fc855": [
      4
    ],
    "df1d2b04": [
      4
    ],
    "6f416a87": [
      4
    ],
    "3a06f06c": [
      4
    ],
    "0209fd4d": [
      4
    ],
    "483d428d": [
      4
    ],
    "58c8dc96": [
      4
    ],
    "49450b6f": [
      4
    ],
    "f2377442": [
      4
    ],
    "67fcd0b8": [
      4
    ],
    "04c58931": [
      4
    ],
    "3008e470": [
      4
    ],
    "75b77094": [
      13
    ],
    "354badf1": [
      13
    ],
    "4dab8e01": [
      13
    ],
    "60a76bf8": [
      13
    ],
    "32c8796e": [
      13
    ],
    "0329f826": [
      13
    ],
    "2b9f2ac7": [
      13
    ],
    "99f06a4a": [
      4
    ],
    "25e214e4": [
      13
    ],
    "136d204c": [
      13
    ],
    "703921b8": [
      13
    ],
    "c50f6e96": [
      13
    ],
    "0acc9e5b": [
      13
    ],
    "4f64c754": [
      13
    ],
    "734dde7e": [
      13
    ],
    "938b8f42": [
      13
    ],
    "6f9bd952": [
      13
    ],
    "4894b8dc": [
      13
    ],
    "9f31f5a6": [
      13
    ],
    "e70059cc": [
      13
    ],
    "4b027e0a": [
      13
    ],
    "d9f17d4c": [
      4
    ],
    "60ba34a0": [
      4
    ],
    "5613c4cc": [
      13
    ],
    "900aa67a": [
      13
    ],
    "337596e4": [
      13
    ],
    "3bfeadf5": [
      13
    ],
    "aa401078": [
      13
    ],
    "f4e9aeac": [
      13
    ],
    "2c1af9b9": [
      13
    ],
    "47fdbf1c": [
      13
    ],
    "2d77d8dd": [
      4
    ],
    "10b2ea6c": [
      13
    ],
    "3b006537": [
      4
    ],
    "607cccd7": [
      4
    ],
    "04bf40dc": [
      4
    ],
    "51a15930": [
      4
    ],
    "00c6e6e6": [
      13
    ],
    "141f192b": [
      13
    ],
    "05face8a": [
      13
    ],
    "3bdb4839": [
      13
    ],
    "f4e522f6": [
      13
    ],
    "65e49c72": [
      13
    ],
    "f4f2c618": [
      13
    ],
    "6c8740a2": [
      13
    ],
    "1f59a592": [
      13
    ],
    "2d9d6196": [
      13
    ],
    "d909705a": [
      13
    ],
    "880bb5ca": [
      13
    ],
    "30c24a64": [
      4
    ],
    "275d62cc": [
      4
    ],
    "41d24eea": [
      4
    ],
    "09d87ccd": [
      4
    ],
    "ad4579d2": [
      4
    ],
    "492fcbf3": [
      4
    ],
    "a51a98e2": [
      4
    ],
    "c0adc192": [
      4
    ],
    "0a6cca35": [
      4
    ],
    "4b5b3459": [
      4
    ],
    "7a479b54": [
      4
    ],
    "19547cce": [
      4
    ],
    "cea960f2": [
      4
    ],
    "6558e360": [
      4
    ],
    "d2fc598c": [
      4
    ],
    "faf9fc2e": [
      13
    ],
    "1b899ad9": [
      13
    ],
    "c02042f6": [
      13
    ],
    "448dd2d8": [
      13
    ],
    "2e848662": [
      13
    ],
    "3d7c58e9": [
      13
    ],
    "2df25c46": [
      13
    ],
    "063bf312": [
      13
    ],
    "647b1b8a": [
      13
    ],
    "1c7a2755": [
      13
    ],
    "0da35f6a": [
      13
    ],
    "00ba32e1": [
      4
    ],
    "59e9edc2": [
      4
    ],
    "24dfb367": [
      13
    ],
    "0ab7130b": [
      13
    ],
    "0ddcc24e": [
      13
    ],
    "2221baf0": [
      13
    ],
    "98f65514": [
      13
    ],
    "7f573ede": [
      13
    ],
    "460fca65": [
      13
    ],
    "76d858cb": [
      13
    ],
    "cc25e5a2": [
      13
    ],
    "613031d0": [
      13
    ],
    "a3f6d4b6": [
      13
    ],
    "17c65434": [
      13
    ],
    "60e4d062": [
      13
    ],
    "16ed2bce": [
      13
    ],
    "1eed5e32": [
      13
    ],
    "52b1ad56": [
      13
    ],
    "be7ad36a": [
      13
    ],
    "02c08bf9": [
      13
    ],
    "523ba2e4": [
      13
    ],
    "61cd276d": [
      13
    ],
    "5fb35304": [
      13
    ],
    "53dca97e": [
      13
    ],
    "1b23095a": [
      13
    ],
    "52a704c8": [
      13
    ],
    "8a8e3938": [
      13
    ],
    "16a7ec2c": [
      13
    ],
    "53ad492c": [
      13
    ],
    "aaa104dc": [
      13
    ],
    "19f68c26": [
      13
    ],
    "a8ed9002": [
      13
    ],
    "7d64b456": [
      13
    ],
    "7afcbdcc": [
      4
    ],
    "fad5fe48": [
      13
    ],
    "59e2aeb3": [
      4
    ],
    "178352b9": [
      4
    ],
    "120f7fe2": [
      4
    ],
    "35c70e3f": [
      4
    ],
    "200d8f17": [
      4
    ],
    "2cd537dc": [
      4
    ],
    "7d586266": [
      4
    ],
    "792fc008": [
      4
    ],
    "0d7e28fc": [
      13
    ],
    "3553e5cb": [
      13
    ],
    "2e93d344": [
      13
    ],
    "04f58c8c": [
      13
    ],
    "51d376b7": [
      13
    ],
    "6fbf9054": [
      13
    ],
    "32c92c77": [
      13
    ],
    "f240de26": [
      13
    ],
    "56f02f18": [
      13
    ],
    "3788df0e": [
      13
    ],
    "5e2e7f02": [
      13
    ],
    "357164c6": [
      13
    ],
    "6a976a5c": [
      13
    ],
    "ee212acc": [
      13
    ],
    "524e2d89": [
      13
    ],
    "71e71075": [
      13
    ],
    "0ad32438": [
      13
    ],
    "da1be296": [
      13
    ],
    "5335205d": [
      13
    ],
    "26dcb466": [
      13
    ],
    "bfbacea4": [
      13
    ],
    "788d27d7": [
      13
    ],
    "0e9c4dc1": [
      13
    ],
    "6952b044": [
      13
    ],
    "507f1bb5": [
      13
    ],
    "62a489fd": [
      13
    ],
    "0e98a032": [
      13
    ],
    "30ee40e4": [
      13
    ],
    "73ff987e": [
      13
    ],
    "2ea9c470": [
      13
    ],
    "18d9d9a6": [
      13
    ],
    "d7d8b30a": [
      13
    ],
    "447891d8": [
      13
    ],
    "e4a79d92": [
      13
    ],
    "c5cc3f4e": [
      13
    ],
    "ae553910": [
      4
    ],
    "51f8f4d5": [
      4
    ],
    "3a0854c4": [
      4
    ],
    "288d02e1": [
      4
    ],
    "65bdeadc": [
      13
    ],
    "17ac257a": [
      13
    ],
    "f2a56226": [
      13
    ],
    "6d3f83f8": [
      13
    ],
    "729ea263": [
      13
    ],
    "ed201778": [
      13
    ],
    "1edd55aa": [
      13
    ],
    "4a777a1b": [
      13
    ],
    "18e35437": [
      13
    ],
    "6c18b9db": [
      13
    ],
    "57cd241c": [
      13
    ],
    "1020c310": [
      13
    ],
    "069e6e1a": [
      13
    ],
    "68339e7f": [
      13
    ],
    "66755f5c": [
      13
    ],
    "7b933e21": [
      4
    ],
    "d8cdce38": [
      4
    ],
    "b3563b3a": [
      4
    ],
    "834a85b4": [
      4
    ],
    "503a5a41": [
      4
    ],
    "a7fc7644": [
      4
    ],
    "3c40191d": [
      4
    ],
    "24f596ba": [
      4
    ],
    "bef9fe8e": [
      4
    ],
    "ed8f0354": [
      4
    ],
    "420df24d": [
      4
    ],
    "1841a1d0": [
      4
    ],
    "6e60bedf": [
      4
    ],
    "e6f932ce": [
      4
    ],
    "362c27fa": [
      4
    ],
    "3a823e40": [
      4
    ],
    "7d3ea35a": [
      4
    ],
    "d63feb3c": [
      4
    ],
    "596b7a58": [
      4
    ],
    "284578de": [
      4
    ],
    "0f7366c0": [
      13
    ],
    "5e79aef4": [
      13
    ],
    "790e92b8": [
      13
    ],
    "09f1c1f4": [
      5
    ],
    "0b46dd72": [
      7
    ],
    "d490aee8": [
      7
    ],
    "7ff0b740": [
      8
    ],
    "8e167898": [
      11
    ],
    "6f18eae6": [
      11
    ],
    "306cd97c": [
      11
    ],
    "679ac344": [
      6
    ],
    "44e7aaf0": [
      6
    ],
    "5fcd005a": [
      6
    ],
    "178540f3": [
      6
    ],
    "880cf71a": [
      10
    ],
    "7063a11d": [
      9
    ],
    "12b144a0": [
      5
    ],
    "6c86420d": [
      5
    ],
    "b07979f0": [
      7
    ],
    "806dc46a": [
      7
    ],
    "66b3f7bc": [
      7
    ],
    "012851e5": [
      7
    ],
    "147bf36a": [
      8
    ],
    "e39996f2": [
      8
    ],
    "62f7a5ca": [
      11
    ],
    "232928cd": [
      11
    ],
    "d7bde492": [
      11
    ],
    "50019e54": [
      11
    ],
    "67364ba6": [
      11
    ],
    "65dd1fc3": [
      11
    ],
    "12b772f0": [
      6
    ],
    "66f7ada5": [
      6
    ],
    "1dec9a1e": [
      6
    ],
    "d0cdfc3e": [
      6
    ],
    "24c1c57d": [
      6
    ],
    "64504d4c": [
      6
    ],
    "4e739c89": [
      6
    ],
    "fa142b68": [
      6
    ],
    "1a7a12c6": [
      10
    ],
    "1d2c6a8c": [
      10
    ],
    "5750d472": [
      9
    ],
    "5beecd24": [
      9
    ],
    "564a2dd4": [
      6
    ],
    "4fbd1e0a": [
      6
    ],
    "25f82d6d": [
      6
    ],
    "1b83f01f": [
      6
    ],
    "52e18356": [
      6
    ],
    "42a17286": [
      6
    ],
    "02c40040": [
      6
    ],
    "b68188fa": [
      6
    ],
    "c8a1ad4a": [
      6
    ],
    "1d0b34ea": [
      6
    ],
    "d69b8988": [
      6
    ],
    "9d76ef8c": [
      6
    ],
    "04bc0492": [
      6
    ],
    "1c413efc": [
      6
    ],
    "1f7fd93e": [
      6
    ],
    "2926129c": [
      6
    ],
    "486a557a": [
      6
    ],
    "7056a454": [
      6
    ],
    "2ff58da8": [
      6
    ],
    "338873ca": [
      11
    ],
    "610bc7fa": [
      11
    ],
    "b9409a82": [
      11
    ],
    "4061c154": [
      11
    ],
    "8cc6b314": [
      11
    ],
    "e8fee79a": [
      11
    ],
    "18f92599": [
      11
    ],
    "89f61108": [
      11
    ],
    "2a2e80ee": [
      11
    ],
    "5f4b9bcb": [
      11
    ],
    "77a71c60": [
      11
    ],
    "1c5b75a0": [
      11
    ],
    "115f8e97": [
      11
    ],
    "0fdac927": [
      11
    ],
    "3f3e8b07": [
      11
    ],
    "99e3a188": [
      7
    ],
    "9ddff51c": [
      7
    ],
    "f15dddf6": [
      7
    ],
    "171af6d4": [
      7
    ],
    "978b3224": [
      7
    ],
    "bc286c4a": [
      7
    ],
    "e4df51a4": [
      7
    ],
    "02041b46": [
      7
    ],
    "1ba37252": [
      7
    ],
    "3ddd0fa2": [
      7
    ],
    "3bef225e": [
      9
    ],
    "144e82ca": [
      9
    ],
    "27cf47ab": [
      9
    ],
    "3f1a1d26": [
      9
    ],
    "7fcdc650": [
      9
    ],
    "fe039246": [
      9
    ],
    "2ea4e671": [
      9
    ],
    "2427b539": [
      9
    ],
    "d7ad4830": [
      9
    ],
    "1c374799": [
      5
    ],
    "974daa9c": [
      5
    ],
    "7ea0ead0": [
      5
    ],
    "41b675e4": [
      5
    ],
    "78f1c747": [
      5
    ],
    "23fecca8": [
      8
    ],
    "650a6eb2": [
      8
    ],
    "dc3659c6": [
      8
    ],
    "0b58e20e": [
      8
    ],
    "3b706dd4": [
      8
    ],
    "52771b3c": [
      10
    ],
    "e818021a": [
      10
    ],
    "4206cf27": [
      10
    ],
    "0ab7564f": [
      10
    ],
    "5843c2de": [
      10
    ],
    "feee80c0": [
      2
    ],
    "8c10d2ae": [
      2
    ],
    "48119d21": [
      2
    ],
    "2f075fa0": [
      2
    ]
  },
  "assetsMapping": {
    "bba68bf6": [
      "10.ba10f2f.js"
    ],
    "1a3ae26b": [
      "app.bafce3c.js"
    ],
    "2aff1868": [
      "pages/about.b419aed.js"
    ],
    "ae0b3444": [
      "pages/blog/_name.2e89b62.js"
    ],
    "acf14974": [
      "pages/blog/index.4949bf2.js"
    ],
    "67c13ec2": [
      "pages/contact.f037173.js"
    ],
    "2a130dde": [
      "pages/index.998eb47.js"
    ],
    "3bf1953c": [
      "pages/portfolio/_name.e743218.js"
    ],
    "3ad7aa6c": [
      "pages/portfolio/index.e66de57.js"
    ],
    "6fca0322": [
      "runtime.7dce548.js"
    ],
    "07a97964": [
      "vendors/commons.797aadd.js"
    ]
  }
}